.gitattributes
.gitignore
LICENSE
MANIFEST.in
Procfile
README.md
codecov.yml
config.cfg
requirements-dev.txt
requirements.txt
setup.py
.github/CODE_OF_CONDUCT.md
.github/ISSUE_TEMPLATE/bug_report.md
.github/workflows/python-publish.yml
.github/workflows/python-test.yml
config/install.sh
docs/Makefile
docs/README.md
docs/README.rst
docs/changelog.rst
docs/conf.py
docs/configuration.rst
docs/contact.rst
docs/developing.rst
docs/functionality.rst
docs/index.rst
docs/installation.rst
docs/known_issues.rst
docs/migration.rst
docs/requirements.txt
docs/todo.rst
docs/img/architecture.png
docs/img/database_scheme.png
docs/img/fmd_db.png
docs/img/fmd_video.gif
docs/img/header.png
docs/img/monitoring_levels.png
docs/img/ss1.png
docs/img/ss2.png
docs/img/ss3.png
docs/img/ss4.png
docs/img/ss5.png
lemonadefashion_Flask_MonitoringDashboard.egg-info/PKG-INFO
lemonadefashion_Flask_MonitoringDashboard.egg-info/SOURCES.txt
lemonadefashion_Flask_MonitoringDashboard.egg-info/dependency_links.txt
lemonadefashion_Flask_MonitoringDashboard.egg-info/entry_points.txt
lemonadefashion_Flask_MonitoringDashboard.egg-info/not-zip-safe
lemonadefashion_Flask_MonitoringDashboard.egg-info/requires.txt
lemonadefashion_Flask_MonitoringDashboard.egg-info/top_level.txt
lemonadefashion_flask_monitoringdashboard/__init__.py
lemonadefashion_flask_monitoringdashboard/cli.py
lemonadefashion_flask_monitoringdashboard/constants.json
lemonadefashion_flask_monitoringdashboard/main.py
lemonadefashion_flask_monitoringdashboard/controllers/__init__.py
lemonadefashion_flask_monitoringdashboard/controllers/endpoints.py
lemonadefashion_flask_monitoringdashboard/controllers/outliers.py
lemonadefashion_flask_monitoringdashboard/controllers/profiler.py
lemonadefashion_flask_monitoringdashboard/controllers/requests.py
lemonadefashion_flask_monitoringdashboard/controllers/versions.py
lemonadefashion_flask_monitoringdashboard/core/__init__.py
lemonadefashion_flask_monitoringdashboard/core/auth.py
lemonadefashion_flask_monitoringdashboard/core/cache.py
lemonadefashion_flask_monitoringdashboard/core/colors.py
lemonadefashion_flask_monitoringdashboard/core/date_interval.py
lemonadefashion_flask_monitoringdashboard/core/get_ip.py
lemonadefashion_flask_monitoringdashboard/core/group_by.py
lemonadefashion_flask_monitoringdashboard/core/logger.py
lemonadefashion_flask_monitoringdashboard/core/measurement.py
lemonadefashion_flask_monitoringdashboard/core/rules.py
