Metadata-Version: 1.2
Name: lemonadefashion-Flask-MonitoringDashboard
Version: 0.5.2
Summary: Automatically monitor the evolving performance of Flask/Python web services.
Home-page: https://github.com/us88/Flask-MonitoringDashboard
Author: Mohamad Ali Baydoun
Author-email: baydoun@lemonadefashion.com
License: UNKNOWN
Project-URL: Bug Reports, https://github.com/us88/Flask-MonitoringDashboard/issues
Project-URL: PyPi, https://pypi.org/project/lemonadefashion-Flask-MonitoringDashboard/
Project-URL: Documentation, http://flask-monitoringdashboard.readthedocs.io/
Project-URL: Source, https://github.com/us88/Flask-MonitoringDashboard/
Platform: Any
Classifier: Environment :: Web Environment
Classifier: Intended Audience :: Developers
Classifier: Operating System :: OS Independent
Classifier: License :: OSI Approved :: MIT License
Classifier: Programming Language :: Python
Classifier: Topic :: Software Development :: Libraries :: Python Modules
Classifier: Programming Language :: Python :: 2.7
Classifier: Programming Language :: Python :: 3.5
Classifier: Programming Language :: Python :: 3.6
Classifier: Programming Language :: Python :: 3.7
Classifier: Programming Language :: Python :: 3.8
Classifier: Framework :: Flask
